deepakGPAconversion
