Metadata-Version: 2.1
Name: deepakGPAconversion
Version: 0.0.3
Summary: A basic GPA to Percentage convertor
Home-page: 
Author: Deepak Tyagi
Author-email: X23178019@student.ncirl.ie
License: MIT
Keywords: convertor
Classifier: Development Status :: 5 - Production/Stable
Classifier: Intended Audience :: Education
Classifier: Operating System :: Microsoft :: Windows :: Windows 10
Classifier: License :: OSI Approved :: MIT License
Classifier: Programming Language :: Python :: 3
License-File: LICENSE.txt
